mispy/__init__.py
mispy/misp.py
mispy-0.5.dist-info/LICENCE
mispy-0.5.dist-info/METADATA
mispy-0.5.dist-info/WHEEL
mispy-0.5.dist-info/top_level.txt
mispy-0.5.dist-info/RECORD
