Metadata-Version: 1.1
Name: mispy
Version: 0.5
Summary: A pythonic MISP module
Home-page: https://github.com/airbus-cert/mispy
Author: Nicolas Bareil
Author-email: nico@chdir.org
License: Apachev2
Download-URL: https://github.com/airbus-cert/mispy/archive/v0.5.tar.gz
Keywords: misp
Platform: UNKNOWN
